README.md
setup.py
cvbuilder/__init__.py
cvbuilder/__version__.py
cvbuilder/builder.py
cvbuilder/cli.py
cvbuilder/systems.py
cvbuilder/utils.py
cvbuilder.egg-info/PKG-INFO
cvbuilder.egg-info/SOURCES.txt
cvbuilder.egg-info/dependency_links.txt
cvbuilder.egg-info/entry_points.txt
cvbuilder.egg-info/requires.txt
cvbuilder.egg-info/top_level.txt
cvbuilder/__syspatch__/__init__.py
cvbuilder/__syspatch__/patched/__init__.py
cvbuilder/__syspatch__/patched/crayons.py
cvbuilder/__syspatch__/vendor/__init__.py
cvbuilder/__syspatch__/vendor/background.py
cvbuilder/__syspatch__/vendor/click_completion.py
cvbuilder/__syspatch__/vendor/docopt.py
cvbuilder/__syspatch__/vendor/first.py
cvbuilder/__syspatch__/vendor/parse.py
cvbuilder/__syspatch__/vendor/semver.py
cvbuilder/__syspatch__/vendor/click/__init__.py
cvbuilder/__syspatch__/vendor/click/_bashcomplete.py
cvbuilder/__syspatch__/vendor/click/_compat.py
cvbuilder/__syspatch__/vendor/click/_termui_impl.py
cvbuilder/__syspatch__/vendor/click/_textwrap.py
cvbuilder/__syspatch__/vendor/click/_unicodefun.py
cvbuilder/__syspatch__/vendor/click/_winconsole.py
cvbuilder/__syspatch__/vendor/click/core.py
cvbuilder/__syspatch__/vendor/click/decorators.py
cvbuilder/__syspatch__/vendor/click/exceptions.py
cvbuilder/__syspatch__/vendor/click/formatting.py
cvbuilder/__syspatch__/vendor/click/globals.py
cvbuilder/__syspatch__/vendor/click/parser.py
cvbuilder/__syspatch__/vendor/click/termui.py
cvbuilder/__syspatch__/vendor/click/testing.py
cvbuilder/__syspatch__/vendor/click/types.py
cvbuilder/__syspatch__/vendor/click/utils.py
cvbuilder/__syspatch__/vendor/click_didyoumean/__init__.py
cvbuilder/__syspatch__/vendor/click_log/__init__.py
cvbuilder/__syspatch__/vendor/click_log/core.py
cvbuilder/__syspatch__/vendor/click_log/options.py
cvbuilder/__syspatch__/vendor/colorama/__init__.py
cvbuilder/__syspatch__/vendor/colorama/ansi.py
cvbuilder/__syspatch__/vendor/colorama/ansitowin32.py
cvbuilder/__syspatch__/vendor/colorama/initialise.py
cvbuilder/__syspatch__/vendor/colorama/win32.py
cvbuilder/__syspatch__/vendor/colorama/winterm.py
cvbuilder/__syspatch__/vendor/pexpect/ANSI.py
cvbuilder/__syspatch__/vendor/pexpect/FSM.py
