Metadata-Version: 2.1
Name: cvbuilder
Version: 0.2.17
Summary: Package for building OpenCV 4.0.0-alpha including Python 3 bindings from the official sources.
Home-page: UNKNOWN
Author: Hannes Römer
Author-email: none@example.org
License: MIT
Keywords: opencv,computer vision
Platform: LINUX
Classifier: Development Status :: 3 - Alpha
Classifier: Environment :: Console
Classifier: Intended Audience :: Developers
Classifier: Intended Audience :: Education
Classifier: Intended Audience :: Information Technology
Classifier: Intended Audience :: Science/Research
Classifier: License :: OSI Approved :: MIT License
Classifier: Operating System :: POSIX
Classifier: Operating System :: Unix
Classifier: Programming Language :: C++
Classifier: Programming Language :: Python
Classifier: Programming Language :: Python :: 3
Classifier: Programming Language :: Python :: 3.4
Classifier: Programming Language :: Python :: 3.5
Classifier: Programming Language :: Python :: 3.6
Classifier: Programming Language :: Python :: 3.7
Classifier: Programming Language :: Python :: Implementation :: CPython
Classifier: Topic :: Scientific/Engineering
Classifier: Topic :: Scientific/Engineering :: Image Recognition
Classifier: Topic :: Software Development
Requires-Python: >=3.4
